spi_master_apb.v
module spi_master_apb (

    input           pclk,
    input           presetn,

    input           psel,
    input           penable,
    input           pwrite,
    input  [31:0]   paddr,
    input  [31:0]   pwdata,

    output reg [31:0] prdata,
    output          pready,

    output reg      sclk,
    output          mosi,
    input           miso,
    output reg      cs_n,

    output          irq

);

reg [7:0] txdata_reg;
reg [7:0] rxdata_reg;
reg [31:0] control_reg;
reg [31:0] status_reg;

reg [7:0] shift_tx;
reg [7:0] shift_rx;

reg [3:0] bit_count;
reg busy;

assign pready = 1'b1;

assign irq = status_reg[1];

assign mosi = shift_tx[7];

wire apb_write;
wire apb_read;

assign apb_write = psel & penable & pwrite;
assign apb_read  = psel & penable & ~pwrite;

always @(posedge pclk or negedge presetn)
begin

    if(!presetn)
    begin

        txdata_reg  <= 0;
        rxdata_reg  <= 0;
        control_reg <= 0;
        status_reg  <= 0;

        shift_tx <= 0;
        shift_rx <= 0;

        bit_count <= 0;

        busy <= 0;

        sclk <= 0;
        cs_n <= 1;

    end

    else
    begin

        //-----------------------------------
        // APB WRITE
        //-----------------------------------

        if(apb_write)
        begin

            case(paddr[7:0])

                8'h00:
                    txdata_reg <= pwdata[7:0];

                8'h08:
                begin

                    control_reg <= pwdata;

                    if(pwdata[0] && !busy)
                    begin

                        shift_tx <= txdata_reg;
                        shift_rx <= 8'h00;

                        bit_count <= 8;

                        busy <= 1;

                        status_reg[0] <= 1;
                        status_reg[1] <= 0;

                        cs_n <= 0;

                    end

                end

            endcase

        end

        //-----------------------------------
        // SPI SHIFT ENGINE
        //-----------------------------------

        if(busy)
        begin

            sclk <= ~sclk;

            if(sclk == 0)
            begin

                shift_rx <= {shift_rx[6:0], miso};
                shift_tx <= {shift_tx[6:0], 1'b0};

                bit_count <= bit_count - 1;

                if(bit_count == 1)
                begin

                    busy <= 0;

                    cs_n <= 1;

                    rxdata_reg <= {shift_rx[6:0], miso};

                    status_reg[0] <= 0;
                    status_reg[1] <= 1;

                end

            end

        end

    end

end

always @(*)
begin

    prdata = 32'h0;

    if(apb_read)
    begin

        case(paddr[7:0])

            8'h00: prdata = {24'd0, txdata_reg};
            8'h04: prdata = {24'd0, rxdata_reg};
            8'h08: prdata = control_reg;
            8'h0C: prdata = status_reg;

            default:
                prdata = 32'hDEADBEEF;

        endcase

    end

end

endmodule

tb_spi_master_apb.v
`timescale 1ns/1ps

module tb_spi_master_apb;

reg pclk;
reg presetn;

reg psel;
reg penable;
reg pwrite;

reg [31:0] paddr;
reg [31:0] pwdata;

wire [31:0] prdata;
wire pready;

wire sclk;
wire mosi;
wire cs_n;

wire irq;

wire miso;

assign miso = mosi;

spi_master_apb DUT (

    .pclk(pclk),
    .presetn(presetn),

    .psel(psel),
    .penable(penable),
    .pwrite(pwrite),
    .paddr(paddr),
    .pwdata(pwdata),

    .prdata(prdata),
    .pready(pready),

    .sclk(sclk),
    .mosi(mosi),
    .miso(miso),
    .cs_n(cs_n),

    .irq(irq)

);

initial
begin
    pclk = 0;
    forever #5 pclk = ~pclk;
end

task apb_write;
input [31:0] addr;
input [31:0] data;
begin

    @(posedge pclk);

    psel=1;
    pwrite=1;
    penable=0;

    paddr=addr;
    pwdata=data;

    @(posedge pclk);

    penable=1;

    @(posedge pclk);

    psel=0;
    penable=0;
    pwrite=0;

end
endtask

task apb_read;
input [31:0] addr;
begin

    @(posedge pclk);

    psel=1;
    pwrite=0;
    penable=0;

    paddr=addr;

    @(posedge pclk);

    penable=1;

    @(posedge pclk);

    $display("READ Addr=%h Data=%h",
              addr,
              prdata);

    psel=0;
    penable=0;

end
endtask

initial
begin

    $dumpfile("spi.vcd");
    $dumpvars(0,tb_spi_master_apb);

    psel=0;
    penable=0;
    pwrite=0;
    paddr=0;
    pwdata=0;

    presetn=0;

    repeat(5) @(posedge pclk);

    presetn=1;

    //--------------------------------
    // TXDATA = A5
    //--------------------------------

    apb_write(32'h00,32'hA5);

    //--------------------------------
    // START
    //--------------------------------

    apb_write(32'h08,32'h1);

    wait(irq);

    $display("SPI TRANSFER COMPLETE");

    apb_read(32'h04);
    apb_read(32'h0C);

    #50;

    $finish;

end

endmodule

spi.vcd
$date
	Thu Jun 18 09:21:11 2026
$end
$version
	Icarus Verilog
$end
$timescale
	1ps
$end
$scope module tb_spi_master_apb $end
$var wire 1 ! miso $end
$var wire 1 " pready $end
$var wire 1 # sclk $end
$var wire 32 $ prdata [31:0] $end
$var wire 1 % mosi $end
$var wire 1 & irq $end
$var wire 1 ' cs_n $end
$var reg 32 ( paddr [31:0] $end
$var reg 1 ) pclk $end
$var reg 1 * penable $end
$var reg 1 + presetn $end
$var reg 1 , psel $end
$var reg 32 - pwdata [31:0] $end
$var reg 1 . pwrite $end
$scope module DUT $end
$var wire 1 / apb_read $end
$var wire 1 0 apb_write $end
$var wire 1 ! miso $end
$var wire 32 1 paddr [31:0] $end
$var wire 1 ) pclk $end
$var wire 1 * penable $end
$var wire 1 " pready $end
$var wire 1 + presetn $end
$var wire 1 , psel $end
$var wire 32 2 pwdata [31:0] $end
$var wire 1 . pwrite $end
$var wire 1 % mosi $end
$var wire 1 & irq $end
$var reg 4 3 bit_count [3:0] $end
$var reg 1 4 busy $end
$var reg 32 5 control_reg [31:0] $end
$var reg 1 ' cs_n $end
$var reg 32 6 prdata [31:0] $end
$var reg 8 7 rxdata_reg [7:0] $end
$var reg 1 # sclk $end
$var reg 8 8 shift_rx [7:0] $end
$var reg 8 9 shift_tx [7:0] $end
$var reg 32 : status_reg [31:0] $end
$var reg 8 ; txdata_reg [7:0] $end
$upscope $end
$scope task apb_read $end
$var reg 32 < addr [31:0] $end
$upscope $end
$scope task apb_write $end
$var reg 32 = addr [31:0] $end
$var reg 32 > data [31:0] $end
$upscope $end
$upscope $end
$enddefinitions $end
$comment Show the parameter values. $end
$dumpall
$end
#0
$dumpvars
bx >
bx =
bx <
b0 ;
b0 :
b0 9
b0 8
b0 7
b0 6
b0 5
04
b0 3
b0 2
b0 1
00
0/
0.
b0 -
0,
0+
0*
0)
b0 (
1'
0&
0%
b0 $
0#
1"
0!
$end
#5000
1)
#10000
0)
#15000
1)
#20000
0)
#25000
1)
#30000
0)
#35000
1)
#40000
0)
#45000
b10100101 >
b0 =
1+
1)
#50000
0)
#55000
b10100101 -
b10100101 2
1.
1,
1)
#60000
0)
#65000
10
1*
1)
#70000
0)
#75000
b10100101 ;
00
b1 >
b1000 =
0.
0*
0,
1)
#80000
0)
#85000
b1 -
b1 2
b1000 (
b1000 1
1.
1,
1)
#90000
0)
#95000
10
1*
1)
#100000
0)
#105000
1!
1%
0'
b1 :
14
b1000 3
b10100101 9
b1 5
00
0.
0*
0,
1)
#110000
0)
#115000
0!
0%
b111 3
b1001010 9
b1 8
1#
1)
#120000
0)
#125000
0#
1)
#130000
0)
#135000
1!
1%
b110 3
b10010100 9
b10 8
1#
1)
#140000
0)
#145000
0#
1)
#150000
0)
#155000
0!
0%
b101 3
b101000 9
b101 8
1#
1)
#160000
0)
#165000
0#
1)
#170000
0)
#175000
b100 3
b1010000 9
b1010 8
1#
1)
#180000
0)
#185000
0#
1)
#190000
0)
#195000
1!
1%
b11 3
b10100000 9
b10100 8
1#
1)
#200000
0)
#205000
0#
1)
#210000
0)
#215000
0!
0%
b10 3
b1000000 9
b101001 8
1#
1)
#220000
0)
#225000
0#
1)
#230000
0)
#235000
1!
1%
b1 3
b10000000 9
b1010010 8
1#
1)
#240000
0)
#245000
0#
1)
#250000
0)
#255000
b100 <
1&
0!
0%
b10 :
b10100101 7
1'
04
b0 3
b0 9
b10100101 8
1#
1)
#260000
0)
#265000
b100 (
b100 1
1,
1)
#270000
0)
#275000
b10100101 $
b10100101 6
1/
1*
1)
#280000
0)
#285000
b0 $
b0 6
0/
b1100 <
0*
0,
1)
#290000
0)
#295000
b1100 (
b1100 1
1,
1)
#300000
0)
#305000
b10 $
b10 6
1/
1*
1)
#310000
0)
#315000
b0 $
b0 6
0/
0*
0,
1)
